rxnpy/__init__.py
rxnpy/constants_en.txt
rxnpy/default_en.txt
rxnpy/chemical/__init__.py
rxnpy/chemical/chemical.py
rxnpy/chemical/element.py
rxnpy/chemical/ingredient.py
rxnpy/chemical/lookup.py
rxnpy/chemical/molecular_formula.py
rxnpy/chemical/periodic_table.py
rxnpy/chemical/lookup_tools/__init__.py
rxnpy/chemical/lookup_tools/pubchem/__init__.py
rxnpy/chemical/lookup_tools/pubchem/extract_pubchem_data.py
rxnpy/chemical/lookup_tools/pubchem/get_pubchem_data_exmples.py
rxnpy/chemical/lookup_tools/pubchem/get_pubchem_lists.py
rxnpy/chemical/lookup_tools/pubchem/pubchem.py
rxnpy/chemical/lookup_tools/pubchem/pubchem_json.py
rxnpy/chemical/lookup_tools/pubchem/pubchem_merge.py
rxnpy/chemical/lookup_tools/pubchem/data/cid_1049.json
rxnpy/chemical/lookup_tools/pubchem/data/cid_1140.json
rxnpy/chemical/lookup_tools/pubchem/data/cid_1146.json
rxnpy/chemical/lookup_tools/pubchem/data/cid_887.json
rxnpy/chemical/lookup_tools/pubchem/data/cid_996.json
rxnpy/chemical/lookup_tools/quantity_parsing/__init__.py
rxnpy/chemical/lookup_tools/quantity_parsing/main.py
rxnpy/chemical/lookup_tools/quantity_parsing/multiple_quantity_finder.py
rxnpy/chemical/lookup_tools/quantity_parsing/post_processing.py
rxnpy/chemical/lookup_tools/quantity_parsing/pre_processing.py
rxnpy/chemical/lookup_tools/quantity_parsing/reduce_quantity_list.py
rxnpy/chemical/lookup_tools/quantity_parsing/sig_figs.py
rxnpy/chemical/lookup_tools/quantity_parsing/testing_utils.py
rxnpy/chemical/lookup_tools/quantity_parsing/to_quantity.py
rxnpy/chemical/lookup_tools/quantity_parsing/utils.py
rxnpy/chemical/lookup_tools/wikipidia/__init__.py
rxnpy/chemical/lookup_tools/wikipidia/wiki_download.py
rxnpy/chemical/lookup_tools/wikipidia/wiki_webscrape.py
rxnpy/chemical/referance_data/__init__.py
rxnpy/chemical/referance_data/elements.txt
rxnpy/data/__init__.py
rxnpy/reaction/__init__.py
rxnpy/reaction/ingredients.py
rxnpy/reaction/tools/__init__.py
rxnpy/reaction/tools/ingredients_calc.py
rxnpy/utilities/__init__.py
rxnpy-0.0.6.dist-info/LICENSE.txt
rxnpy-0.0.6.dist-info/METADATA
rxnpy-0.0.6.dist-info/WHEEL
rxnpy-0.0.6.dist-info/top_level.txt
rxnpy-0.0.6.dist-info/RECORD
